mcp_sqlite_memory_bank/__init__.py
mcp_sqlite_memory_bank/__main__.py
mcp_sqlite_memory_bank/database.py
mcp_sqlite_memory_bank/graph_analyzer.py
mcp_sqlite_memory_bank/graph_tools.py
mcp_sqlite_memory_bank/prompts.py
mcp_sqlite_memory_bank/py.typed
mcp_sqlite_memory_bank/resources.py
mcp_sqlite_memory_bank/self_healing.py
mcp_sqlite_memory_bank/semantic.py
mcp_sqlite_memory_bank/server.py
mcp_sqlite_memory_bank/types.py
mcp_sqlite_memory_bank/utils.py
mcp_sqlite_memory_bank/tools/__init__.py
mcp_sqlite_memory_bank/tools/analytics.py
mcp_sqlite_memory_bank/tools/basic.py
mcp_sqlite_memory_bank/tools/d3_visualization.py
mcp_sqlite_memory_bank/tools/discovery.py
mcp_sqlite_memory_bank/tools/llm_optimization.py
mcp_sqlite_memory_bank/tools/optimization.py
mcp_sqlite_memory_bank/tools/search.py
mcp_sqlite_memory_bank/tools/visualization.py
mcp_sqlite_memory_bank-1.6.12.dist-info/licenses/LICENSE
mcp_sqlite_memory_bank-1.6.12.dist-info/METADATA
mcp_sqlite_memory_bank-1.6.12.dist-info/WHEEL
mcp_sqlite_memory_bank-1.6.12.dist-info/entry_points.txt
mcp_sqlite_memory_bank-1.6.12.dist-info/top_level.txt
mcp_sqlite_memory_bank-1.6.12.dist-info/RECORD
