Metadata-Version: 2.4
Name: mcp_sqlite_memory_bank
Version: 1.6.12
Summary: A dynamic, agent/LLM-friendly SQLite memory bank for MCP servers with semantic search capabilities.
Author-email: Robert Meisner <robert@catchit.pl>
License-Expression: MIT
Project-URL: Homepage, https://github.com/robertmeisner/mcp_sqlite_memory_bank
Project-URL: Source, https://github.com/robertmeisner/mcp_sqlite_memory_bank
Project-URL: Issues, https://github.com/robertmeisner/mcp_sqlite_memory_bank/issues
Classifier: Programming Language :: Python :: 3
Classifier: Operating System :: OS Independent
Requires-Python: >=3.10
License-File: LICENSE
Requires-Dist: fastapi>=0.100.0
Requires-Dist: uvicorn>=0.22.0
Requires-Dist: pydantic>=1.10.0
Requires-Dist: fastmcp>=2.9.0
Requires-Dist: sqlalchemy>=2.0.0
Requires-Dist: sentence-transformers>=2.2.0
Requires-Dist: torch>=1.9.0
Provides-Extra: test
Requires-Dist: pytest; extra == "test"
Dynamic: license-file
